[

{
"id" : "join_mission",
"name" : "회원 가입하기 미션",
"description" : "회원 가입 1회 완료시 권한을 획득하는 미션",
"activityId" : "join",
"reward_type" : "permission_type",
"reward_object" : "write_permission",
"reward_parameter" : 1,
"exit_condition" : 1,
"ruleId" : "countOne",
"isRepeatable" : false,
"repeat_period" : 0,
"max_repeat_count" : 0,
"useConstraint" : false,
"constraint_period" : 0,
"isContinuous" : false,
"useExpiration" : false,
"start_date" : null,
"end_date" : null
},
{  
"id" : "login_mission",
"name" : "로그인하기 미션",
"description" : "로그인 10회 완료시 배지를 획득하는 미션",
"activityId" : "login",
"reward_type" : "badge_type",
"reward_object" : "login_badge",
"reward_parameter" : 1,
"exit_condition" : 10,
"ruleId" : "countOne",
"isRepeatable" : false,
"repeat_period" : 0,
"max_repeat_count" : 0,
"useConstraint" : true,
"constraint_period" : 1,
"isContinuous" : false,
"useExpiration" : false,
"start_date" : null,
"end_date" : null
},
{  
  "id" : "sponsor_mission",
  "name" : "후원하기 미션",
  "description" : "후원 1회 완료시 포인트를 획득하는 미션",
  "activityId" : "sponsor",
  "reward_type" : "point_type",
  "reward_object" : "sponsor_point",
  "reward_parameter" : 10000,
  "exit_condition" : 1,
  "ruleId" : "countOne",
  "isRepeatable" : true,
  "repeat_period" : 0,
  "max_repeat_count" : 0,
  "useConstraint" : false,
  "constraint_period" : 0,
  "isContinuous" : false,
  "useExpiration" : false,
  "start_date" : null,
  "end_date" : null
},
{  
  "id" : "watch_mission",
  "name" : "방송보기 미션",
  "description" : "방송 시청 50회 완료시 배지를  획득하는 미션",
  "activityId" : "watch",
  "reward_type" : "badge_type",
  "reward_object" : "watch_badge",
  "reward_parameter" : 1,
  "exit_condition" : 50,
  "ruleId" : "countOne",
  "isRepeatable" : false,
  "repeat_period" : 0,
  "max_repeat_count" : 0,
  "useConstraint" : true,
  "constraint_period" : 1,
  "isContinuous" : false,
  "useExpiration" : false,
  "start_date" : null,
  "end_date" : null
},
{  
  "id" : "comment_mission",
  "name" : "덧글 달기 미션",
  "description" : "덧글 작성 30회 완료시 배지를 획득하는 미션",
  "activityId" : "comment",
  "reward_type" : "badge_type",
  "reward_object" : "comment_badge",
  "reward_parameter" : 1,
  "exit_condition" : 30,
  "ruleId" : "countOne",
  "isRepeatable" : false,
  "repeat_period" : 0,
  "max_repeat_count" : 0,
  "useConstraint" : false,
  "constraint_period" : 0,
  "isContinuous" : false,
  "useExpiration" : false,
  "start_date" : null,
  "end_date" : null
}

]